markdown_live_server-0.1.1.dist-info/licenses/LICENSE
mdv/__init__.py
mdv/cli.py
mdv/server.py
markdown_live_server-0.1.1.dist-info/METADATA
markdown_live_server-0.1.1.dist-info/WHEEL
markdown_live_server-0.1.1.dist-info/entry_points.txt
markdown_live_server-0.1.1.dist-info/top_level.txt
markdown_live_server-0.1.1.dist-info/RECORD
