Metadata-Version: 2.4
Name: markdown-live-server
Version: 0.1.1
Summary: Markdown live server with live reload using Pandoc
License: MIT
Project-URL: Homepage, https://github.com/mfyz/mdv
Project-URL: Repository, https://github.com/mfyz/mdv
Keywords: markdown,pandoc,live-reload,server
Classifier: Development Status :: 4 - Beta
Classifier: Environment :: Console
Classifier: Environment :: Web Environment
Classifier: Intended Audience :: Developers
Classifier: License :: OSI Approved :: MIT License
Classifier: Programming Language :: Python :: 3
Classifier: Programming Language :: Python :: 3.8
Classifier: Programming Language :: Python :: 3.9
Classifier: Programming Language :: Python :: 3.10
Classifier: Programming Language :: Python :: 3.11
Classifier: Programming Language :: Python :: 3.12
Classifier: Topic :: Text Processing :: Markup :: Markdown
Requires-Python: >=3.8
License-File: LICENSE
Requires-Dist: bottle
Dynamic: license-file
